{"accuracy": 0.03994447011430719, "rgb": "#79868b", "cb": 0, "words": [{"text": "hollow", "color": "#00ffbb", "initloc": {"y": 0, "x": 0}, "size": 0.0008538274560123682}, {"text": "tail", "color": "#28ff60", "initloc": {"y": 0, "x": 0}, "size": 0.0008552035433240235}, {"text": "side", "color": "#1cc240", "initloc": {"y": 0, "x": 0}, "size": 0.0008558337576687336}, {"text": "large", "color": "#00ff00", "initloc": {"y": 0, "x": 0}, "size": 0.0008560062269680202}, {"text": "blue", "color": "#00ff3d", "initloc": {"y": 0, "x": 0}, "size": 0.0008779551717452705}, {"text": "white", "color": "#45ff35", "initloc": {"y": 0, "x": 0}, "size": 0.0009338571690022945}, {"text": "perched", "color": "#1be83f", "initloc": {"y": 0, "x": 0}, "size": 0.0008627083152532578}, {"text": "fastened", "color": "#22ff19", "initloc": {"y": 0, "x": 0}, "size": 0.0008736172458156943}, {"text": "ground", "color": "#00ff4d", "initloc": {"y": 0, "x": 0}, "size": 0.0010620702523738146}, {"text": "beneath", "color": "#00ff9e", "initloc": {"y": 0, "x": 0}, "size": 0.0010031412821263075}, {"text": "fire", "color": "#44b87b", "initloc": {"y": 0, "x": 0}, "size": 0.0009198648622259498}, {"text": "green", "color": "#00ff2f", "initloc": {"y": 0, "x": 0}, "size": 0.0009159292094409466}, {"text": "sand", "color": "#00ff9d", "initloc": {"y": 0, "x": 0}, "size": 0.0009009485365822911}, {"text": "red", "color": "#0cff38", "initloc": {"y": 0, "x": 0}, "size": 0.0009709500591270626}, {"text": "head", "color": "#87e27a", "initloc": {"y": 0, "x": 0}, "size": 0.0008660610765218735}, {"text": "atop", "color": "#00ff36", "initloc": {"y": 0, "x": 0}, "size": 0.0008664916967973113}, {"text": "arms", "color": "#89ff63", "initloc": {"y": 0, "x": 0}, "size": 0.0009664645185694098}, {"text": "yellow", "color": "#00ff3b", "initloc": {"y": 0, "x": 0}, "size": 0.0009017633274197578}, {"text": "heads", "color": "#56ff71", "initloc": {"y": 0, "x": 0}, "size": 0.0008710077963769436}, {"text": "black", "color": "#4bff37", "initloc": {"y": 0, "x": 0}, "size": 0.0009339478565379977}], "ctm_idx": 60476, "freesurfer_idx": 127008, "hemi": "left"}