{"accuracy": 0.2440196127135723, "rgb": "#3ff185", "cb": 3, "words": [{"text": "rubber", "color": "#01ff41", "initloc": {"y": 0, "x": 0}, "size": 0.014292677864432335}, {"text": "colored", "color": "#00ff3e", "initloc": {"y": 0, "x": 0}, "size": 0.014500873163342476}, {"text": "fabric", "color": "#00ff5b", "initloc": {"y": 0, "x": 0}, "size": 0.014314506202936172}, {"text": "steel", "color": "#00ff39", "initloc": {"y": 0, "x": 0}, "size": 0.014490446075797081}, {"text": "soft", "color": "#00ffd1", "initloc": {"y": 0, "x": 0}, "size": 0.014366148971021175}, {"text": "shape", "color": "#00ffa6", "initloc": {"y": 0, "x": 0}, "size": 0.014504320919513702}, {"text": "layer", "color": "#00ff9a", "initloc": {"y": 0, "x": 0}, "size": 0.015034055337309837}, {"text": "diameter", "color": "#00ff40", "initloc": {"y": 0, "x": 0}, "size": 0.014850249513983727}, {"text": "shaped", "color": "#00ff7e", "initloc": {"y": 0, "x": 0}, "size": 0.014618776738643646}, {"text": "thin", "color": "#03ffab", "initloc": {"y": 0, "x": 0}, "size": 0.01469377987086773}, {"text": "thicker", "color": "#05ffb9", "initloc": {"y": 0, "x": 0}, "size": 0.014941513538360596}, {"text": "layered", "color": "#00ff9e", "initloc": {"y": 0, "x": 0}, "size": 0.014701513573527336}, {"text": "surfaces", "color": "#00ff8e", "initloc": {"y": 0, "x": 0}, "size": 0.014710619114339352}, {"text": "combination", "color": "#02ffaa", "initloc": {"y": 0, "x": 0}, "size": 0.014867184683680534}, {"text": "smooth", "color": "#00ffda", "initloc": {"y": 0, "x": 0}, "size": 0.015093857422471046}, {"text": "metallic", "color": "#00ff9d", "initloc": {"y": 0, "x": 0}, "size": 0.016130689531564713}, {"text": "edges", "color": "#00ff6f", "initloc": {"y": 0, "x": 0}, "size": 0.015571363270282745}, {"text": "metal", "color": "#00ff82", "initloc": {"y": 0, "x": 0}, "size": 0.01518735010176897}, {"text": "layers", "color": "#00ffa6", "initloc": {"y": 0, "x": 0}, "size": 0.01510052289813757}, {"text": "coloured", "color": "#00ff34", "initloc": {"y": 0, "x": 0}, "size": 0.01521572470664978}], "ctm_idx": 89334, "freesurfer_idx": 94973, "hemi": "left"}