{"accuracy": 0.08909211637879576, "rgb": "#646361", "cb": 1, "words": [{"text": "downtown", "color": "#004d00", "initloc": {"y": 0, "x": 0}, "size": 0.00862120557576418}, {"text": "building", "color": "#004200", "initloc": {"y": 0, "x": 0}, "size": 0.008731858804821968}, {"text": "park", "color": "#007e00", "initloc": {"y": 0, "x": 0}, "size": 0.009572536684572697}, {"text": "pier", "color": "#006519", "initloc": {"y": 0, "x": 0}, "size": 0.008763081394135952}, {"text": "moved", "color": "#770003", "initloc": {"y": 0, "x": 0}, "size": 0.009068617597222328}, {"text": "street", "color": "#286a00", "initloc": {"y": 0, "x": 0}, "size": 0.009179271757602692}, {"text": "city", "color": "#277200", "initloc": {"y": 0, "x": 0}, "size": 0.009456362575292587}, {"text": "entrance", "color": "#004300", "initloc": {"y": 0, "x": 0}, "size": 0.008910125121474266}, {"text": "west", "color": "#119502", "initloc": {"y": 0, "x": 0}, "size": 0.008752919733524323}, {"text": "opened", "color": "#093005", "initloc": {"y": 0, "x": 0}, "size": 0.009375253692269325}, {"text": "hotel", "color": "#540000", "initloc": {"y": 0, "x": 0}, "size": 0.009182357229292393}, {"text": "home", "color": "#8d0000", "initloc": {"y": 0, "x": 0}, "size": 0.008757142350077629}, {"text": "hall", "color": "#113a00", "initloc": {"y": 0, "x": 0}, "size": 0.009554325602948666}, {"text": "town", "color": "#484000", "initloc": {"y": 0, "x": 0}, "size": 0.009549899026751518}, {"text": "north", "color": "#09a008", "initloc": {"y": 0, "x": 0}, "size": 0.008807120844721794}, {"text": "nearby", "color": "#175c00", "initloc": {"y": 0, "x": 0}, "size": 0.009979483671486378}, {"text": "road", "color": "#006600", "initloc": {"y": 0, "x": 0}, "size": 0.009273731149733067}, {"text": "inn", "color": "#491500", "initloc": {"y": 0, "x": 0}, "size": 0.008897656574845314}, {"text": "station", "color": "#005a00", "initloc": {"y": 0, "x": 0}, "size": 0.008745628409087658}, {"text": "near", "color": "#1f6e14", "initloc": {"y": 0, "x": 0}, "size": 0.0093984454870224}], "ctm_idx": 50959, "freesurfer_idx": 215778, "hemi": "right"}