{"accuracy": 0.10792628354626047, "rgb": "#516ea0", "cb": 2, "words": [{"text": "fog", "color": "#0082bc", "initloc": {"y": 0, "x": 0}, "size": 0.004828295204788446}, {"text": "towers", "color": "#00713c", "initloc": {"y": 0, "x": 0}, "size": 0.004861165303736925}, {"text": "scenery", "color": "#0068a4", "initloc": {"y": 0, "x": 0}, "size": 0.004863745998591185}, {"text": "space", "color": "#005a56", "initloc": {"y": 0, "x": 0}, "size": 0.004875023849308491}, {"text": "directions", "color": "#007d74", "initloc": {"y": 0, "x": 0}, "size": 0.00491269351914525}, {"text": "storage", "color": "#009f1c", "initloc": {"y": 0, "x": 0}, "size": 0.005225491244345903}, {"text": "paths", "color": "#00519c", "initloc": {"y": 0, "x": 0}, "size": 0.004926030058413744}, {"text": "atmosphere", "color": "#0077f0", "initloc": {"y": 0, "x": 0}, "size": 0.005018116906285286}, {"text": "humidity", "color": "#00da9c", "initloc": {"y": 0, "x": 0}, "size": 0.004945370834320784}, {"text": "roads", "color": "#00733b", "initloc": {"y": 0, "x": 0}, "size": 0.00491793267428875}, {"text": "stream", "color": "#00bba4", "initloc": {"y": 0, "x": 0}, "size": 0.005915464833378792}, {"text": "tunnels", "color": "#008f68", "initloc": {"y": 0, "x": 0}, "size": 0.005615677684545517}, {"text": "streams", "color": "#00e481", "initloc": {"y": 0, "x": 0}, "size": 0.005405418574810028}, {"text": "windows", "color": "#005961", "initloc": {"y": 0, "x": 0}, "size": 0.005133519414812326}, {"text": "corridors", "color": "#003964", "initloc": {"y": 0, "x": 0}, "size": 0.005404174327850342}, {"text": "overhead", "color": "#00ad31", "initloc": {"y": 0, "x": 0}, "size": 0.005146135576069355}, {"text": "blocks", "color": "#00a421", "initloc": {"y": 0, "x": 0}, "size": 0.005244398955255747}, {"text": "concrete", "color": "#00eda3", "initloc": {"y": 0, "x": 0}, "size": 0.004912835080176592}, {"text": "block", "color": "#00b121", "initloc": {"y": 0, "x": 0}, "size": 0.005093328654766083}, {"text": "flow", "color": "#00f0db", "initloc": {"y": 0, "x": 0}, "size": 0.005092368461191654}], "ctm_idx": 107479, "freesurfer_idx": 243858, "hemi": "right"}