{"accuracy": 0.09969116585223606, "rgb": "#5e9d9e", "cb": 1, "words": [{"text": "compressed", "color": "#00ffa4", "initloc": {"y": 0, "x": 0}, "size": 0.006250666454434395}, {"text": "produces", "color": "#00ff8c", "initloc": {"y": 0, "x": 0}, "size": 0.0062879943288862705}, {"text": "areas", "color": "#00c831", "initloc": {"y": 0, "x": 0}, "size": 0.006328280549496412}, {"text": "rapid", "color": "#00e291", "initloc": {"y": 0, "x": 0}, "size": 0.006345910020172596}, {"text": "terrain", "color": "#00d162", "initloc": {"y": 0, "x": 0}, "size": 0.006599581800401211}, {"text": "edges", "color": "#00ff6f", "initloc": {"y": 0, "x": 0}, "size": 0.006608431227505207}, {"text": "relatively", "color": "#00ef83", "initloc": {"y": 0, "x": 0}, "size": 0.006596689112484455}, {"text": "streams", "color": "#00e481", "initloc": {"y": 0, "x": 0}, "size": 0.006469197105616331}, {"text": "cooling", "color": "#00f98a", "initloc": {"y": 0, "x": 0}, "size": 0.006620896048843861}, {"text": "flow", "color": "#00f0db", "initloc": {"y": 0, "x": 0}, "size": 0.007256764452904463}, {"text": "temperature", "color": "#00f9a2", "initloc": {"y": 0, "x": 0}, "size": 0.006787053309381008}, {"text": "surfaces", "color": "#00ff8e", "initloc": {"y": 0, "x": 0}, "size": 0.007160271517932415}, {"text": "range", "color": "#00ff28", "initloc": {"y": 0, "x": 0}, "size": 0.0066476138308644295}, {"text": "diameter", "color": "#00ff40", "initloc": {"y": 0, "x": 0}, "size": 0.006622293032705784}, {"text": "surface", "color": "#00ff93", "initloc": {"y": 0, "x": 0}, "size": 0.007545563858002424}, {"text": "currents", "color": "#00c2aa", "initloc": {"y": 0, "x": 0}, "size": 0.006662121508270502}, {"text": "vertical", "color": "#00ff44", "initloc": {"y": 0, "x": 0}, "size": 0.006689512170851231}, {"text": "layers", "color": "#00ffa6", "initloc": {"y": 0, "x": 0}, "size": 0.0066462112590670586}, {"text": "dense", "color": "#00ffcf", "initloc": {"y": 0, "x": 0}, "size": 0.007055000402033329}, {"text": "layer", "color": "#00ff9a", "initloc": {"y": 0, "x": 0}, "size": 0.0067846504971385}], "ctm_idx": 44043, "freesurfer_idx": 134861, "hemi": "left"}