{"accuracy": -0.0014260581756957936, "rgb": "#7f789e", "cb": 0, "words": [{"text": "sounds", "color": "#d34dff", "initloc": {"y": 0, "x": 0}, "size": 0.0025275233201682568}, {"text": "believe", "color": "#ff3cff", "initloc": {"y": 0, "x": 0}, "size": 0.0025449716486036777}, {"text": "disorder", "color": "#ff56ff", "initloc": {"y": 0, "x": 0}, "size": 0.0025600711815059185}, {"text": "sad", "color": "#ec16ff", "initloc": {"y": 0, "x": 0}, "size": 0.0025781504809856415}, {"text": "fact", "color": "#ff46f1", "initloc": {"y": 0, "x": 0}, "size": 0.0025839090812951326}, {"text": "feelings", "color": "#ff00ff", "initloc": {"y": 0, "x": 0}, "size": 0.002581682289019227}, {"text": "sincerity", "color": "#ec31ff", "initloc": {"y": 0, "x": 0}, "size": 0.0026058945804834366}, {"text": "true", "color": "#fe5bff", "initloc": {"y": 0, "x": 0}, "size": 0.002610932569950819}, {"text": "deeply", "color": "#e346ff", "initloc": {"y": 0, "x": 0}, "size": 0.002614672062918544}, {"text": "mental", "color": "#ff10ff", "initloc": {"y": 0, "x": 0}, "size": 0.002624708926305175}, {"text": "cruel", "color": "#ff68ff", "initloc": {"y": 0, "x": 0}, "size": 0.002626091707497835}, {"text": "speaking", "color": "#f400ff", "initloc": {"y": 0, "x": 0}, "size": 0.0026327981613576412}, {"text": "understood", "color": "#e216ff", "initloc": {"y": 0, "x": 0}, "size": 0.0026711528189480305}, {"text": "truly", "color": "#e92eff", "initloc": {"y": 0, "x": 0}, "size": 0.002642892301082611}, {"text": "truth", "color": "#ff22ff", "initloc": {"y": 0, "x": 0}, "size": 0.0026711230166256428}, {"text": "emotional", "color": "#fe22ff", "initloc": {"y": 0, "x": 0}, "size": 0.0026889571454375982}, {"text": "profound", "color": "#b438ff", "initloc": {"y": 0, "x": 0}, "size": 0.0027070166543126106}, {"text": "indeed", "color": "#f933ff", "initloc": {"y": 0, "x": 0}, "size": 0.0030250144191086292}, {"text": "life", "color": "#ff00e1", "initloc": {"y": 0, "x": 0}, "size": 0.0027461519930511713}, {"text": "perhaps", "color": "#e834ff", "initloc": {"y": 0, "x": 0}, "size": 0.0028069077525287867}], "ctm_idx": 26516, "freesurfer_idx": 105297, "hemi": "left"}