{"accuracy": 0.02967727702169259, "rgb": "#679795", "cb": 0, "words": [{"text": "vertical", "color": "#00ff44", "initloc": {"y": 0, "x": 0}, "size": 0.003983910195529461}, {"text": "dense", "color": "#00ffcf", "initloc": {"y": 0, "x": 0}, "size": 0.003991022240370512}, {"text": "elements", "color": "#00ddba", "initloc": {"y": 0, "x": 0}, "size": 0.004017752595245838}, {"text": "shape", "color": "#00ffa6", "initloc": {"y": 0, "x": 0}, "size": 0.004042388871312141}, {"text": "such", "color": "#5ed5ab", "initloc": {"y": 0, "x": 0}, "size": 0.004045278765261173}, {"text": "metallic", "color": "#00ff9d", "initloc": {"y": 0, "x": 0}, "size": 0.004010630305856466}, {"text": "material", "color": "#00ff90", "initloc": {"y": 0, "x": 0}, "size": 0.004042528569698334}, {"text": "wide", "color": "#00ff3d", "initloc": {"y": 0, "x": 0}, "size": 0.004081180319190025}, {"text": "combination", "color": "#02ffaa", "initloc": {"y": 0, "x": 0}, "size": 0.004085542634129524}, {"text": "form", "color": "#2dff72", "initloc": {"y": 0, "x": 0}, "size": 0.0042723496444523335}, {"text": "contrast", "color": "#00ff95", "initloc": {"y": 0, "x": 0}, "size": 0.004095584154129028}, {"text": "itself", "color": "#35b8f7", "initloc": {"y": 0, "x": 0}, "size": 0.004104171879589558}, {"text": "surface", "color": "#00ff93", "initloc": {"y": 0, "x": 0}, "size": 0.0046221609227359295}, {"text": "layers", "color": "#00ffa6", "initloc": {"y": 0, "x": 0}, "size": 0.004103288985788822}, {"text": "characteristic", "color": "#28ffd2", "initloc": {"y": 0, "x": 0}, "size": 0.004324913956224918}, {"text": "surfaces", "color": "#00ff8e", "initloc": {"y": 0, "x": 0}, "size": 0.004116546828299761}, {"text": "shapes", "color": "#00ffc9", "initloc": {"y": 0, "x": 0}, "size": 0.004474231973290443}, {"text": "edges", "color": "#00ff6f", "initloc": {"y": 0, "x": 0}, "size": 0.004209863021969795}, {"text": "diameter", "color": "#00ff40", "initloc": {"y": 0, "x": 0}, "size": 0.004091848153620958}, {"text": "layer", "color": "#00ff9a", "initloc": {"y": 0, "x": 0}, "size": 0.004158885683864355}], "ctm_idx": 136693, "freesurfer_idx": 322862, "hemi": "right"}