{"accuracy": 0.08440660222897084, "rgb": "#7d7e99", "cb": 1, "words": [{"text": "citizens", "color": "#ec4477", "initloc": {"y": 0, "x": 0}, "size": 0.005034377798438072}, {"text": "understanding", "color": "#a01eff", "initloc": {"y": 0, "x": 0}, "size": 0.005041582975536585}, {"text": "rational", "color": "#ed26ff", "initloc": {"y": 0, "x": 0}, "size": 0.005046755075454712}, {"text": "argue", "color": "#e954ff", "initloc": {"y": 0, "x": 0}, "size": 0.005092857405543327}, {"text": "truly", "color": "#e92eff", "initloc": {"y": 0, "x": 0}, "size": 0.005075160879641771}, {"text": "ignorant", "color": "#ff61ff", "initloc": {"y": 0, "x": 0}, "size": 0.005054902285337448}, {"text": "religious", "color": "#ff0dfa", "initloc": {"y": 0, "x": 0}, "size": 0.00509604811668396}, {"text": "interests", "color": "#a240a4", "initloc": {"y": 0, "x": 0}, "size": 0.0052336337976157665}, {"text": "humanity", "color": "#c73eff", "initloc": {"y": 0, "x": 0}, "size": 0.005412707105278969}, {"text": "beliefs", "color": "#ff30ff", "initloc": {"y": 0, "x": 0}, "size": 0.005205841735005379}, {"text": "ignorance", "color": "#ef56ff", "initloc": {"y": 0, "x": 0}, "size": 0.005205459892749786}, {"text": "belief", "color": "#ff54ff", "initloc": {"y": 0, "x": 0}, "size": 0.005251761060208082}, {"text": "benefit", "color": "#a37699", "initloc": {"y": 0, "x": 0}, "size": 0.00528706656768918}, {"text": "compassion", "color": "#ff32ff", "initloc": {"y": 0, "x": 0}, "size": 0.005342530552297831}, {"text": "americans", "color": "#cb71cd", "initloc": {"y": 0, "x": 0}, "size": 0.005251522175967693}, {"text": "moral", "color": "#ff4bfb", "initloc": {"y": 0, "x": 0}, "size": 0.005334171932190657}, {"text": "politicians", "color": "#e26bbb", "initloc": {"y": 0, "x": 0}, "size": 0.005202263128012419}, {"text": "beings", "color": "#cb56ff", "initloc": {"y": 0, "x": 0}, "size": 0.005161109380424023}, {"text": "religion", "color": "#ff32ff", "initloc": {"y": 0, "x": 0}, "size": 0.005227180197834969}, {"text": "consequences", "color": "#ff2ff0", "initloc": {"y": 0, "x": 0}, "size": 0.005226918496191502}], "ctm_idx": 66885, "freesurfer_idx": 93731, "hemi": "left"}