{"accuracy": 0.014422890660050274, "rgb": "#7a858f", "cb": 0, "words": [{"text": "they're", "color": "#bd7fb4", "initloc": {"y": 0, "x": 0}, "size": 0.001749151386320591}, {"text": "yeah", "color": "#bd67d4", "initloc": {"y": 0, "x": 0}, "size": 0.0017517959931865335}, {"text": "shit", "color": "#b373aa", "initloc": {"y": 0, "x": 0}, "size": 0.0017526594456285238}, {"text": "guess", "color": "#cd3fd1", "initloc": {"y": 0, "x": 0}, "size": 0.001760848332196474}, {"text": "you'll", "color": "#9042bd", "initloc": {"y": 0, "x": 0}, "size": 0.0017537367530167103}, {"text": "try", "color": "#963dc7", "initloc": {"y": 0, "x": 0}, "size": 0.001761127496138215}, {"text": "okay", "color": "#ef31e8", "initloc": {"y": 0, "x": 0}, "size": 0.0017645969055593014}, {"text": "it'd", "color": "#7675d3", "initloc": {"y": 0, "x": 0}, "size": 0.0017608185298740864}, {"text": "anyway", "color": "#da0bc1", "initloc": {"y": 0, "x": 0}, "size": 0.0017702681943774223}, {"text": "they'll", "color": "#c15792", "initloc": {"y": 0, "x": 0}, "size": 0.00177623494528234}, {"text": "it'll", "color": "#5c80d3", "initloc": {"y": 0, "x": 0}, "size": 0.0019177193753421307}, {"text": "ok", "color": "#d636e8", "initloc": {"y": 0, "x": 0}, "size": 0.0018194366712123156}, {"text": "you'd", "color": "#a76aa9", "initloc": {"y": 0, "x": 0}, "size": 0.0018571692053228617}, {"text": "gotta", "color": "#8494c3", "initloc": {"y": 0, "x": 0}, "size": 0.0017759855836629868}, {"text": "stuff", "color": "#5c6bb0", "initloc": {"y": 0, "x": 0}, "size": 0.0018643137300387025}, {"text": "won't", "color": "#e93ec6", "initloc": {"y": 0, "x": 0}, "size": 0.0017903217813000083}, {"text": "piss", "color": "#8a68a1", "initloc": {"y": 0, "x": 0}, "size": 0.0017711608670651913}, {"text": "crap", "color": "#8f7ec7", "initloc": {"y": 0, "x": 0}, "size": 0.0018430184572935104}, {"text": "whatever", "color": "#a25bb0", "initloc": {"y": 0, "x": 0}, "size": 0.0018073327373713255}, {"text": "suck", "color": "#959af2", "initloc": {"y": 0, "x": 0}, "size": 0.0017904021078720689}], "ctm_idx": 59952, "freesurfer_idx": 170559, "hemi": "right"}