{"accuracy": 0.13606201466875845, "rgb": "#598a91", "cb": 2, "words": [{"text": "layers", "color": "#00ffa6", "initloc": {"y": 0, "x": 0}, "size": 0.004961801692843437}, {"text": "humidity", "color": "#00da9c", "initloc": {"y": 0, "x": 0}, "size": 0.005079218186438084}, {"text": "dense", "color": "#00ffcf", "initloc": {"y": 0, "x": 0}, "size": 0.005031078588217497}, {"text": "low", "color": "#00ff70", "initloc": {"y": 0, "x": 0}, "size": 0.005013602320104837}, {"text": "vertical", "color": "#00ff44", "initloc": {"y": 0, "x": 0}, "size": 0.005063946358859539}, {"text": "relatively", "color": "#00ef83", "initloc": {"y": 0, "x": 0}, "size": 0.005050191655755043}, {"text": "currents", "color": "#00c2aa", "initloc": {"y": 0, "x": 0}, "size": 0.005074537359178066}, {"text": "range", "color": "#00ff28", "initloc": {"y": 0, "x": 0}, "size": 0.005081824492663145}, {"text": "layer", "color": "#00ff9a", "initloc": {"y": 0, "x": 0}, "size": 0.005137331783771515}, {"text": "flow", "color": "#00f0db", "initloc": {"y": 0, "x": 0}, "size": 0.005450110882520676}, {"text": "surface", "color": "#00ff93", "initloc": {"y": 0, "x": 0}, "size": 0.006029367446899414}, {"text": "heat", "color": "#00ff96", "initloc": {"y": 0, "x": 0}, "size": 0.005283535458147526}, {"text": "large", "color": "#00ff00", "initloc": {"y": 0, "x": 0}, "size": 0.005327702034264803}, {"text": "surfaces", "color": "#00ff8e", "initloc": {"y": 0, "x": 0}, "size": 0.005570834502577782}, {"text": "heavy", "color": "#00ffa5", "initloc": {"y": 0, "x": 0}, "size": 0.00532137556001544}, {"text": "water", "color": "#00ff80", "initloc": {"y": 0, "x": 0}, "size": 0.005232227500528097}, {"text": "wide", "color": "#00ff3d", "initloc": {"y": 0, "x": 0}, "size": 0.005163246300071478}, {"text": "edges", "color": "#00ff6f", "initloc": {"y": 0, "x": 0}, "size": 0.005255764815956354}, {"text": "cooling", "color": "#00f98a", "initloc": {"y": 0, "x": 0}, "size": 0.005140888970345259}, {"text": "temperature", "color": "#00f9a2", "initloc": {"y": 0, "x": 0}, "size": 0.005375227890908718}], "ctm_idx": 108002, "freesurfer_idx": 123231, "hemi": "left"}