{"accuracy": 0.060806626806539144, "rgb": "#716180", "cb": 1, "words": [{"text": "moved", "color": "#770003", "initloc": {"y": 0, "x": 0}, "size": 0.0031284368596971035}, {"text": "afternoon", "color": "#1b0024", "initloc": {"y": 0, "x": 0}, "size": 0.003128543496131897}, {"text": "next", "color": "#680000", "initloc": {"y": 0, "x": 0}, "size": 0.003144823480397463}, {"text": "evening", "color": "#27000b", "initloc": {"y": 0, "x": 0}, "size": 0.0031708786264061928}, {"text": "meet", "color": "#9c003d", "initloc": {"y": 0, "x": 0}, "size": 0.003196600591763854}, {"text": "at", "color": "#641e00", "initloc": {"y": 0, "x": 0}, "size": 0.0032767036464065313}, {"text": "visiting", "color": "#a10019", "initloc": {"y": 0, "x": 0}, "size": 0.003278853837400675}, {"text": "came", "color": "#b10053", "initloc": {"y": 0, "x": 0}, "size": 0.003375622211024165}, {"text": "where", "color": "#5e0e14", "initloc": {"y": 0, "x": 0}, "size": 0.0034445151686668396}, {"text": "day", "color": "#540021", "initloc": {"y": 0, "x": 0}, "size": 0.003429034259170294}, {"text": "place", "color": "#450000", "initloc": {"y": 0, "x": 0}, "size": 0.0033861359115689993}, {"text": "lived", "color": "#ff002c", "initloc": {"y": 0, "x": 0}, "size": 0.003401568392291665}, {"text": "hotel", "color": "#540000", "initloc": {"y": 0, "x": 0}, "size": 0.003495636396110058}, {"text": "home", "color": "#8d0000", "initloc": {"y": 0, "x": 0}, "size": 0.004706460516899824}, {"text": "school", "color": "#6d0000", "initloc": {"y": 0, "x": 0}, "size": 0.0035966348368674517}, {"text": "visit", "color": "#bf0012", "initloc": {"y": 0, "x": 0}, "size": 0.003638454247266054}, {"text": "trip", "color": "#53000e", "initloc": {"y": 0, "x": 0}, "size": 0.0036287587136030197}, {"text": "went", "color": "#950019", "initloc": {"y": 0, "x": 0}, "size": 0.0039584459736943245}, {"text": "night", "color": "#5b0043", "initloc": {"y": 0, "x": 0}, "size": 0.0034991768188774586}, {"text": "house", "color": "#9f0000", "initloc": {"y": 0, "x": 0}, "size": 0.003881114535033703}], "ctm_idx": 87520, "freesurfer_idx": 31415, "hemi": "left"}