{"accuracy": 0.061163269877728424, "rgb": "#78788e", "cb": 1, "words": [{"text": "youth", "color": "#916568", "initloc": {"y": 0, "x": 0}, "size": 0.002262209542095661}, {"text": "studied", "color": "#a627a0", "initloc": {"y": 0, "x": 0}, "size": 0.0022673301864415407}, {"text": "experiences", "color": "#8d00ff", "initloc": {"y": 0, "x": 0}, "size": 0.002269564662128687}, {"text": "philosophy", "color": "#a920f9", "initloc": {"y": 0, "x": 0}, "size": 0.002293843775987625}, {"text": "spiritual", "color": "#b516ff", "initloc": {"y": 0, "x": 0}, "size": 0.0022866358049213886}, {"text": "scholars", "color": "#ac3893", "initloc": {"y": 0, "x": 0}, "size": 0.0022775521501898766}, {"text": "literature", "color": "#923baf", "initloc": {"y": 0, "x": 0}, "size": 0.00228256662376225}, {"text": "graduate", "color": "#74151f", "initloc": {"y": 0, "x": 0}, "size": 0.002298978390172124}, {"text": "academic", "color": "#482f36", "initloc": {"y": 0, "x": 0}, "size": 0.002477706875652075}, {"text": "schools", "color": "#695400", "initloc": {"y": 0, "x": 0}, "size": 0.002546289935708046}, {"text": "pursue", "color": "#d70092", "initloc": {"y": 0, "x": 0}, "size": 0.0023112017661333084}, {"text": "opportunities", "color": "#53245f", "initloc": {"y": 0, "x": 0}, "size": 0.002369316527619958}, {"text": "colleges", "color": "#3d5000", "initloc": {"y": 0, "x": 0}, "size": 0.002438582945615053}, {"text": "influenced", "color": "#74b4f6", "initloc": {"y": 0, "x": 0}, "size": 0.002389892702922225}, {"text": "respected", "color": "#ee37b8", "initloc": {"y": 0, "x": 0}, "size": 0.002357573015615344}, {"text": "diverse", "color": "#08c0b2", "initloc": {"y": 0, "x": 0}, "size": 0.002448461949825287}, {"text": "teaching", "color": "#ad009d", "initloc": {"y": 0, "x": 0}, "size": 0.0023600622080266476}, {"text": "culture", "color": "#8eb5f3", "initloc": {"y": 0, "x": 0}, "size": 0.0023019772488623857}, {"text": "education", "color": "#9a244f", "initloc": {"y": 0, "x": 0}, "size": 0.002620096318423748}, {"text": "community", "color": "#4d1658", "initloc": {"y": 0, "x": 0}, "size": 0.0026665946934372187}], "ctm_idx": 83437, "freesurfer_idx": 106638, "hemi": "left"}