{"accuracy": 0.08171939165994076, "rgb": "#5c9481", "cb": 1, "words": [{"text": "varying", "color": "#00ff81", "initloc": {"y": 0, "x": 0}, "size": 0.006307283416390419}, {"text": "divided", "color": "#1bbb07", "initloc": {"y": 0, "x": 0}, "size": 0.006316682789474726}, {"text": "regions", "color": "#00f050", "initloc": {"y": 0, "x": 0}, "size": 0.00633428618311882}, {"text": "structure", "color": "#00d088", "initloc": {"y": 0, "x": 0}, "size": 0.006355037447065115}, {"text": "domes", "color": "#00f746", "initloc": {"y": 0, "x": 0}, "size": 0.006363392807543278}, {"text": "meters", "color": "#00fd1f", "initloc": {"y": 0, "x": 0}, "size": 0.006423568818718195}, {"text": "produces", "color": "#00ff8c", "initloc": {"y": 0, "x": 0}, "size": 0.006514108274132013}, {"text": "maximum", "color": "#00e41d", "initloc": {"y": 0, "x": 0}, "size": 0.006425036117434502}, {"text": "forming", "color": "#00ff83", "initloc": {"y": 0, "x": 0}, "size": 0.006481866352260113}, {"text": "additional", "color": "#00c500", "initloc": {"y": 0, "x": 0}, "size": 0.006398798897862434}, {"text": "resulting", "color": "#3dff62", "initloc": {"y": 0, "x": 0}, "size": 0.006537784822285175}, {"text": "surface", "color": "#00ff93", "initloc": {"y": 0, "x": 0}, "size": 0.006584951654076576}, {"text": "diameter", "color": "#00ff40", "initloc": {"y": 0, "x": 0}, "size": 0.007222415413707495}, {"text": "roughly", "color": "#00f50c", "initloc": {"y": 0, "x": 0}, "size": 0.006710275541990995}, {"text": "approximately", "color": "#00db00", "initloc": {"y": 0, "x": 0}, "size": 0.007337793707847595}, {"text": "formation", "color": "#00f667", "initloc": {"y": 0, "x": 0}, "size": 0.006954742129892111}, {"text": "forms", "color": "#0eff8d", "initloc": {"y": 0, "x": 0}, "size": 0.0066201938316226006}, {"text": "range", "color": "#00ff28", "initloc": {"y": 0, "x": 0}, "size": 0.006644294131547213}, {"text": "combined", "color": "#00ff59", "initloc": {"y": 0, "x": 0}, "size": 0.00689531909301877}, {"text": "addition", "color": "#00e100", "initloc": {"y": 0, "x": 0}, "size": 0.006607620045542717}], "ctm_idx": 106955, "freesurfer_idx": 241767, "hemi": "right"}