{"accuracy": 0.08888834300645342, "rgb": "#6d987f", "cb": 1, "words": [{"text": "lined", "color": "#00fc13", "initloc": {"y": 0, "x": 0}, "size": 0.003977299202233553}, {"text": "fitted", "color": "#00ff07", "initloc": {"y": 0, "x": 0}, "size": 0.003982208203524351}, {"text": "vertical", "color": "#00ff44", "initloc": {"y": 0, "x": 0}, "size": 0.003984516486525536}, {"text": "cylinder", "color": "#00ff22", "initloc": {"y": 0, "x": 0}, "size": 0.003985617309808731}, {"text": "mounted", "color": "#00ff00", "initloc": {"y": 0, "x": 0}, "size": 0.004008149728178978}, {"text": "tops", "color": "#00ff11", "initloc": {"y": 0, "x": 0}, "size": 0.00400794530287385}, {"text": "flattened", "color": "#00ff68", "initloc": {"y": 0, "x": 0}, "size": 0.0040157632902264595}, {"text": "edges", "color": "#00ff6f", "initloc": {"y": 0, "x": 0}, "size": 0.0040638502687215805}, {"text": "tube", "color": "#00ff6b", "initloc": {"y": 0, "x": 0}, "size": 0.004098529927432537}, {"text": "metal", "color": "#00ff82", "initloc": {"y": 0, "x": 0}, "size": 0.0040197973139584064}, {"text": "inch", "color": "#00ff3c", "initloc": {"y": 0, "x": 0}, "size": 0.004233784042298794}, {"text": "rubber", "color": "#01ff41", "initloc": {"y": 0, "x": 0}, "size": 0.004068877547979355}, {"text": "leather", "color": "#00ff0f", "initloc": {"y": 0, "x": 0}, "size": 0.004154159687459469}, {"text": "yellow", "color": "#00ff3b", "initloc": {"y": 0, "x": 0}, "size": 0.004077123478055}, {"text": "steel", "color": "#00ff39", "initloc": {"y": 0, "x": 0}, "size": 0.004216856323182583}, {"text": "inches", "color": "#00ff2e", "initloc": {"y": 0, "x": 0}, "size": 0.004252663813531399}, {"text": "underneath", "color": "#00ff65", "initloc": {"y": 0, "x": 0}, "size": 0.004234598949551582}, {"text": "mm", "color": "#00ff33", "initloc": {"y": 0, "x": 0}, "size": 0.004047960974276066}, {"text": "wire", "color": "#0fff15", "initloc": {"y": 0, "x": 0}, "size": 0.00402233749628067}, {"text": "trim", "color": "#00ff14", "initloc": {"y": 0, "x": 0}, "size": 0.004102284554392099}], "ctm_idx": 890, "freesurfer_idx": 176998, "hemi": "right"}