{"accuracy": 0.024501052279028532, "rgb": "#747d90", "cb": 0, "words": [{"text": "more", "color": "#717f8c", "initloc": {"y": 0, "x": 0}, "size": 0.0016079437918961048}, {"text": "however", "color": "#d25659", "initloc": {"y": 0, "x": 0}, "size": 0.0016104693058878183}, {"text": "common", "color": "#58ec79", "initloc": {"y": 0, "x": 0}, "size": 0.001612708205357194}, {"text": "are", "color": "#789f5c", "initloc": {"y": 0, "x": 0}, "size": 0.001744727836921811}, {"text": "effect", "color": "#49d5ff", "initloc": {"y": 0, "x": 0}, "size": 0.0017430131556466222}, {"text": "nature", "color": "#847bff", "initloc": {"y": 0, "x": 0}, "size": 0.0018265536054968834}, {"text": "especially", "color": "#70a8ff", "initloc": {"y": 0, "x": 0}, "size": 0.0016253434587270021}, {"text": "possible", "color": "#7c3bc6", "initloc": {"y": 0, "x": 0}, "size": 0.001653249142691493}, {"text": "most", "color": "#65a174", "initloc": {"y": 0, "x": 0}, "size": 0.001802563900128007}, {"text": "these", "color": "#498e74", "initloc": {"y": 0, "x": 0}, "size": 0.001838751952163875}, {"text": "many", "color": "#7a5f76", "initloc": {"y": 0, "x": 0}, "size": 0.0018544364720582962}, {"text": "often", "color": "#38d373", "initloc": {"y": 0, "x": 0}, "size": 0.0017444172408431768}, {"text": "such", "color": "#5ed5ab", "initloc": {"y": 0, "x": 0}, "size": 0.0019580035004764795}, {"text": "itself", "color": "#35b8f7", "initloc": {"y": 0, "x": 0}, "size": 0.001822600606828928}, {"text": "human", "color": "#f1a7ff", "initloc": {"y": 0, "x": 0}, "size": 0.0016157141653820872}, {"text": "particular", "color": "#6e68c9", "initloc": {"y": 0, "x": 0}, "size": 0.0016285302117466927}, {"text": "may", "color": "#b08769", "initloc": {"y": 0, "x": 0}, "size": 0.001661062240600586}, {"text": "difficult", "color": "#5f5eff", "initloc": {"y": 0, "x": 0}, "size": 0.001631450722925365}, {"text": "very", "color": "#7363d4", "initloc": {"y": 0, "x": 0}, "size": 0.001655890024267137}, {"text": "particularly", "color": "#49cceb", "initloc": {"y": 0, "x": 0}, "size": 0.001701907953247428}], "ctm_idx": 162245, "freesurfer_idx": 280771, "hemi": "right"}