{"accuracy": 0.10158976618279078, "rgb": "#758a74", "cb": 2, "words": [{"text": "sub", "color": "#0cd678", "initloc": {"y": 0, "x": 0}, "size": 0.00396097544580698}, {"text": "contrast", "color": "#00ff95", "initloc": {"y": 0, "x": 0}, "size": 0.00399116100743413}, {"text": "between", "color": "#19c415", "initloc": {"y": 0, "x": 0}, "size": 0.00443496648222208}, {"text": "e", "color": "#40d342", "initloc": {"y": 0, "x": 0}, "size": 0.004291790537536144}, {"text": "each", "color": "#038700", "initloc": {"y": 0, "x": 0}, "size": 0.004949913825839758}, {"text": "form", "color": "#2dff72", "initloc": {"y": 0, "x": 0}, "size": 0.0049536507576704025}, {"text": "g", "color": "#30ff43", "initloc": {"y": 0, "x": 0}, "size": 0.00451241061091423}, {"text": "may", "color": "#b08769", "initloc": {"y": 0, "x": 0}, "size": 0.0040376135148108006}, {"text": "given", "color": "#f94a40", "initloc": {"y": 0, "x": 0}, "size": 0.004302452318370342}, {"text": "however", "color": "#d25659", "initloc": {"y": 0, "x": 0}, "size": 0.004178553819656372}, {"text": "number", "color": "#5c9f00", "initloc": {"y": 0, "x": 0}, "size": 0.005110814236104488}, {"text": "appear", "color": "#7dd282", "initloc": {"y": 0, "x": 0}, "size": 0.004087807144969702}, {"text": "standard", "color": "#10f621", "initloc": {"y": 0, "x": 0}, "size": 0.004346623085439205}, {"text": "example", "color": "#5fcc7f", "initloc": {"y": 0, "x": 0}, "size": 0.004654979333281517}, {"text": "which", "color": "#45ac0a", "initloc": {"y": 0, "x": 0}, "size": 0.0046658082865178585}, {"text": "forms", "color": "#0eff8d", "initloc": {"y": 0, "x": 0}, "size": 0.0040510790422558784}, {"text": "such", "color": "#5ed5ab", "initloc": {"y": 0, "x": 0}, "size": 0.004024098627269268}, {"text": "although", "color": "#9c9473", "initloc": {"y": 0, "x": 0}, "size": 0.0039954520761966705}, {"text": "thus", "color": "#7fcc61", "initloc": {"y": 0, "x": 0}, "size": 0.004717483650892973}, {"text": "length", "color": "#00ff34", "initloc": {"y": 0, "x": 0}, "size": 0.004243708215653896}], "ctm_idx": 52095, "freesurfer_idx": 146307, "hemi": "left"}