{"accuracy": 0.062149809237467185, "rgb": "#807ca3", "cb": 1, "words": [{"text": "condescending", "color": "#eb32ff", "initloc": {"y": 0, "x": 0}, "size": 0.0053548370487987995}, {"text": "appreciate", "color": "#a612ff", "initloc": {"y": 0, "x": 0}, "size": 0.005356953479349613}, {"text": "certainly", "color": "#ff3fff", "initloc": {"y": 0, "x": 0}, "size": 0.005366556346416473}, {"text": "obvious", "color": "#d961ff", "initloc": {"y": 0, "x": 0}, "size": 0.00536109134554863}, {"text": "saying", "color": "#ff2fff", "initloc": {"y": 0, "x": 0}, "size": 0.005371466279029846}, {"text": "aware", "color": "#ff02ff", "initloc": {"y": 0, "x": 0}, "size": 0.005385267548263073}, {"text": "ignorant", "color": "#ff61ff", "initloc": {"y": 0, "x": 0}, "size": 0.005387669429183006}, {"text": "genuinely", "color": "#e71bff", "initloc": {"y": 0, "x": 0}, "size": 0.005390997510403395}, {"text": "seem", "color": "#c739ff", "initloc": {"y": 0, "x": 0}, "size": 0.005376353859901428}, {"text": "question", "color": "#ff0cf0", "initloc": {"y": 0, "x": 0}, "size": 0.005394698586314917}, {"text": "offended", "color": "#ff36ff", "initloc": {"y": 0, "x": 0}, "size": 0.005478868260979652}, {"text": "ignore", "color": "#f929ff", "initloc": {"y": 0, "x": 0}, "size": 0.005511263385415077}, {"text": "honest", "color": "#ff2dff", "initloc": {"y": 0, "x": 0}, "size": 0.005679794121533632}, {"text": "understand", "color": "#e21fff", "initloc": {"y": 0, "x": 0}, "size": 0.005987190641462803}, {"text": "admit", "color": "#f826ff", "initloc": {"y": 0, "x": 0}, "size": 0.005544612184166908}, {"text": "honestly", "color": "#d630ff", "initloc": {"y": 0, "x": 0}, "size": 0.005556014366447926}, {"text": "explain", "color": "#e20aff", "initloc": {"y": 0, "x": 0}, "size": 0.005515389144420624}, {"text": "believe", "color": "#ff3cff", "initloc": {"y": 0, "x": 0}, "size": 0.0054247453808784485}, {"text": "wrong", "color": "#ff3fff", "initloc": {"y": 0, "x": 0}, "size": 0.005475264973938465}, {"text": "agree", "color": "#ff3fff", "initloc": {"y": 0, "x": 0}, "size": 0.005764101166278124}], "ctm_idx": 93477, "freesurfer_idx": 302285, "hemi": "right"}