{"accuracy": 0.06804949638783929, "rgb": "#9e90a4", "cb": 1, "words": [{"text": "he's", "color": "#ff59c3", "initloc": {"y": 0, "x": 0}, "size": 0.012134881690144539}, {"text": "seem", "color": "#c739ff", "initloc": {"y": 0, "x": 0}, "size": 0.012181967496871948}, {"text": "god", "color": "#ff36ff", "initloc": {"y": 0, "x": 0}, "size": 0.012243237346410751}, {"text": "kind", "color": "#c363fc", "initloc": {"y": 0, "x": 0}, "size": 0.012413125485181808}, {"text": "not", "color": "#ea459f", "initloc": {"y": 0, "x": 0}, "size": 0.012327955104410648}, {"text": "sense", "color": "#c050ff", "initloc": {"y": 0, "x": 0}, "size": 0.012370135635137558}, {"text": "people", "color": "#ce39b5", "initloc": {"y": 0, "x": 0}, "size": 0.012322762981057167}, {"text": "seems", "color": "#dd40ff", "initloc": {"y": 0, "x": 0}, "size": 0.01227534655481577}, {"text": "reason", "color": "#f025ea", "initloc": {"y": 0, "x": 0}, "size": 0.012272652238607407}, {"text": "know", "color": "#ef1ad4", "initloc": {"y": 0, "x": 0}, "size": 0.012630256824195385}, {"text": "though", "color": "#c73ce5", "initloc": {"y": 0, "x": 0}, "size": 0.01277444139122963}, {"text": "because", "color": "#d14ab3", "initloc": {"y": 0, "x": 0}, "size": 0.012716312892735004}, {"text": "being", "color": "#f740b3", "initloc": {"y": 0, "x": 0}, "size": 0.012727398425340652}, {"text": "believe", "color": "#ff3cff", "initloc": {"y": 0, "x": 0}, "size": 0.01349266991019249}, {"text": "isn't", "color": "#dc76f5", "initloc": {"y": 0, "x": 0}, "size": 0.01271955668926239}, {"text": "think", "color": "#db46ee", "initloc": {"y": 0, "x": 0}, "size": 0.013243617489933968}, {"text": "fact", "color": "#ff46f1", "initloc": {"y": 0, "x": 0}, "size": 0.013642733916640282}, {"text": "mean", "color": "#da6dff", "initloc": {"y": 0, "x": 0}, "size": 0.01295190304517746}, {"text": "true", "color": "#fe5bff", "initloc": {"y": 0, "x": 0}, "size": 0.012792563997209072}, {"text": "bad", "color": "#f26bff", "initloc": {"y": 0, "x": 0}, "size": 0.013225964270532131}], "ctm_idx": 63836, "freesurfer_idx": 125289, "hemi": "left"}