{"accuracy": 0.05794683603454966, "rgb": "#788cb0", "cb": 1, "words": [{"text": "ironic", "color": "#ee87ff", "initloc": {"y": 0, "x": 0}, "size": 0.0038466015830636024}, {"text": "translated", "color": "#b38bd1", "initloc": {"y": 0, "x": 0}, "size": 0.003865532111376524}, {"text": "abstract", "color": "#6e8eff", "initloc": {"y": 0, "x": 0}, "size": 0.0038659211713820696}, {"text": "specifically", "color": "#9f99df", "initloc": {"y": 0, "x": 0}, "size": 0.003877549897879362}, {"text": "inspiration", "color": "#6277f3", "initloc": {"y": 0, "x": 0}, "size": 0.0039375899359583855}, {"text": "copied", "color": "#60738d", "initloc": {"y": 0, "x": 0}, "size": 0.0038803424686193466}, {"text": "dictionary", "color": "#9c72a9", "initloc": {"y": 0, "x": 0}, "size": 0.003930928651243448}, {"text": "interpret", "color": "#9e41ff", "initloc": {"y": 0, "x": 0}, "size": 0.003940073773264885}, {"text": "copyright", "color": "#9f7e94", "initloc": {"y": 0, "x": 0}, "size": 0.004026700276881456}, {"text": "reference", "color": "#89a3cb", "initloc": {"y": 0, "x": 0}, "size": 0.003977413289248943}, {"text": "quoted", "color": "#e063f2", "initloc": {"y": 0, "x": 0}, "size": 0.004168624524027109}, {"text": "referring", "color": "#d1b1ff", "initloc": {"y": 0, "x": 0}, "size": 0.004740084521472454}, {"text": "existed", "color": "#9b4bd3", "initloc": {"y": 0, "x": 0}, "size": 0.004116124473512173}, {"text": "translation", "color": "#c05feb", "initloc": {"y": 0, "x": 0}, "size": 0.004355806391686201}, {"text": "references", "color": "#8e7dd9", "initloc": {"y": 0, "x": 0}, "size": 0.004508422687649727}, {"text": "refer", "color": "#9de6b3", "initloc": {"y": 0, "x": 0}, "size": 0.00398705480620265}, {"text": "linked", "color": "#7777c1", "initloc": {"y": 0, "x": 0}, "size": 0.004668958485126495}, {"text": "exists", "color": "#8e5afe", "initloc": {"y": 0, "x": 0}, "size": 0.0041692438535392284}, {"text": "significance", "color": "#6e78c4", "initloc": {"y": 0, "x": 0}, "size": 0.00414374191313982}, {"text": "describing", "color": "#ae61ff", "initloc": {"y": 0, "x": 0}, "size": 0.004091748967766762}], "ctm_idx": 49699, "freesurfer_idx": 304905, "hemi": "right"}