{"accuracy": 0.06453906352934115, "rgb": "#7f6d95", "cb": 1, "words": [{"text": "feelings", "color": "#ff00ff", "initloc": {"y": 0, "x": 0}, "size": 0.0037531352136284113}, {"text": "honest", "color": "#ff2dff", "initloc": {"y": 0, "x": 0}, "size": 0.003759735729545355}, {"text": "sincerely", "color": "#f922ff", "initloc": {"y": 0, "x": 0}, "size": 0.003762975102290511}, {"text": "appreciate", "color": "#a612ff", "initloc": {"y": 0, "x": 0}, "size": 0.003767675720155239}, {"text": "opinions", "color": "#ed4eff", "initloc": {"y": 0, "x": 0}, "size": 0.0037688619922846556}, {"text": "sincere", "color": "#ee21ff", "initloc": {"y": 0, "x": 0}, "size": 0.003772345371544361}, {"text": "truth", "color": "#ff22ff", "initloc": {"y": 0, "x": 0}, "size": 0.003787240944802761}, {"text": "truly", "color": "#e92eff", "initloc": {"y": 0, "x": 0}, "size": 0.003853350877761841}, {"text": "speaking", "color": "#f400ff", "initloc": {"y": 0, "x": 0}, "size": 0.0038961246609687805}, {"text": "forgive", "color": "#ff0cff", "initloc": {"y": 0, "x": 0}, "size": 0.003881983458995819}, {"text": "questions", "color": "#ca00ce", "initloc": {"y": 0, "x": 0}, "size": 0.003984307870268822}, {"text": "interested", "color": "#b900d2", "initloc": {"y": 0, "x": 0}, "size": 0.0038196805398911238}, {"text": "apologize", "color": "#ff00f7", "initloc": {"y": 0, "x": 0}, "size": 0.0037960768677294254}, {"text": "informed", "color": "#ff00be", "initloc": {"y": 0, "x": 0}, "size": 0.0038315020501613617}, {"text": "acknowledge", "color": "#ff15ff", "initloc": {"y": 0, "x": 0}, "size": 0.003868511412292719}, {"text": "questioning", "color": "#ff00ff", "initloc": {"y": 0, "x": 0}, "size": 0.0038109212182462215}, {"text": "genuinely", "color": "#e71bff", "initloc": {"y": 0, "x": 0}, "size": 0.0038780909962952137}, {"text": "discuss", "color": "#cf00cb", "initloc": {"y": 0, "x": 0}, "size": 0.0040434286929667}, {"text": "speak", "color": "#ff00ff", "initloc": {"y": 0, "x": 0}, "size": 0.00408041849732399}, {"text": "religious", "color": "#ff0dfa", "initloc": {"y": 0, "x": 0}, "size": 0.0038050832226872444}], "ctm_idx": 98972, "freesurfer_idx": 47846, "hemi": "left"}