{"accuracy": 0.021467865981534176, "rgb": "#788085", "cb": 0, "words": [{"text": "grand", "color": "#597300", "initloc": {"y": 0, "x": 0}, "size": 0.0008586806943640113}, {"text": "entered", "color": "#751900", "initloc": {"y": 0, "x": 0}, "size": 0.0008600176079198718}, {"text": "university", "color": "#443700", "initloc": {"y": 0, "x": 0}, "size": 0.0008822476374916732}, {"text": "following", "color": "#733b00", "initloc": {"y": 0, "x": 0}, "size": 0.000911372946575284}, {"text": "club", "color": "#2e6c00", "initloc": {"y": 0, "x": 0}, "size": 0.0008622671011835337}, {"text": "york", "color": "#647000", "initloc": {"y": 0, "x": 0}, "size": 0.0008905079448595643}, {"text": "moscow", "color": "#832917", "initloc": {"y": 0, "x": 0}, "size": 0.0008887533331289887}, {"text": "hall", "color": "#113a00", "initloc": {"y": 0, "x": 0}, "size": 0.0009035853436216712}, {"text": "academy", "color": "#6c542d", "initloc": {"y": 0, "x": 0}, "size": 0.000861222913954407}, {"text": "st", "color": "#4a8300", "initloc": {"y": 0, "x": 0}, "size": 0.0009084300836548209}, {"text": "completed", "color": "#0d5100", "initloc": {"y": 0, "x": 0}, "size": 0.0008842850802466273}, {"text": "oxford", "color": "#62520c", "initloc": {"y": 0, "x": 0}, "size": 0.000877743645105511}, {"text": "new", "color": "#186300", "initloc": {"y": 0, "x": 0}, "size": 0.0008845663978718221}, {"text": "march", "color": "#688000", "initloc": {"y": 0, "x": 0}, "size": 0.0008782981894910336}, {"text": "fourth", "color": "#5ca500", "initloc": {"y": 0, "x": 0}, "size": 0.0008615790866315365}, {"text": "memorial", "color": "#3a5618", "initloc": {"y": 0, "x": 0}, "size": 0.0008723444771021605}, {"text": "villa", "color": "#4f4100", "initloc": {"y": 0, "x": 0}, "size": 0.0008910787873901427}, {"text": "london", "color": "#683d00", "initloc": {"y": 0, "x": 0}, "size": 0.0009426806354895234}, {"text": "th", "color": "#3d7500", "initloc": {"y": 0, "x": 0}, "size": 0.0009130222024396062}, {"text": "paris", "color": "#971c10", "initloc": {"y": 0, "x": 0}, "size": 0.0008993636583909392}], "ctm_idx": 6986, "freesurfer_idx": 298768, "hemi": "right"}