{"accuracy": 0.03190490775827661, "rgb": "#80709e", "cb": 0, "words": [{"text": "doubt", "color": "#ff2cff", "initloc": {"y": 0, "x": 0}, "size": 0.0038006994873285294}, {"text": "seem", "color": "#c739ff", "initloc": {"y": 0, "x": 0}, "size": 0.0038087288849055767}, {"text": "truth", "color": "#ff22ff", "initloc": {"y": 0, "x": 0}, "size": 0.003862266428768635}, {"text": "mind", "color": "#c004ff", "initloc": {"y": 0, "x": 0}, "size": 0.0038075088523328304}, {"text": "feelings", "color": "#ff00ff", "initloc": {"y": 0, "x": 0}, "size": 0.003995663486421108}, {"text": "believe", "color": "#ff3cff", "initloc": {"y": 0, "x": 0}, "size": 0.003982612397521734}, {"text": "agree", "color": "#ff3fff", "initloc": {"y": 0, "x": 0}, "size": 0.0038128432352095842}, {"text": "aware", "color": "#ff02ff", "initloc": {"y": 0, "x": 0}, "size": 0.0038257180713117123}, {"text": "knowing", "color": "#fc00ff", "initloc": {"y": 0, "x": 0}, "size": 0.003943318501114845}, {"text": "understand", "color": "#e21fff", "initloc": {"y": 0, "x": 0}, "size": 0.004160525277256966}, {"text": "truly", "color": "#e92eff", "initloc": {"y": 0, "x": 0}, "size": 0.0038493629544973373}, {"text": "speak", "color": "#ff00ff", "initloc": {"y": 0, "x": 0}, "size": 0.004079985432326794}, {"text": "wrong", "color": "#ff3fff", "initloc": {"y": 0, "x": 0}, "size": 0.0038163720164448023}, {"text": "seems", "color": "#dd40ff", "initloc": {"y": 0, "x": 0}, "size": 0.0038348727393895388}, {"text": "thoughts", "color": "#b300ff", "initloc": {"y": 0, "x": 0}, "size": 0.0038040357176214457}, {"text": "fact", "color": "#ff46f1", "initloc": {"y": 0, "x": 0}, "size": 0.003818697761744261}, {"text": "situation", "color": "#ff00d0", "initloc": {"y": 0, "x": 0}, "size": 0.003954146523028612}, {"text": "saying", "color": "#ff2fff", "initloc": {"y": 0, "x": 0}, "size": 0.00394101720303297}, {"text": "honest", "color": "#ff2dff", "initloc": {"y": 0, "x": 0}, "size": 0.0038506134878844023}, {"text": "personally", "color": "#e141ff", "initloc": {"y": 0, "x": 0}, "size": 0.0038195247761905193}], "ctm_idx": 27831, "freesurfer_idx": 282185, "hemi": "right"}