{"accuracy": 0.07542907887096897, "rgb": "#8d8caf", "cb": 1, "words": [{"text": "dislike", "color": "#e46cff", "initloc": {"y": 0, "x": 0}, "size": 0.009413279592990875}, {"text": "deserve", "color": "#ff5aea", "initloc": {"y": 0, "x": 0}, "size": 0.009428679943084717}, {"text": "sentiment", "color": "#ec56ff", "initloc": {"y": 0, "x": 0}, "size": 0.009436598978936672}, {"text": "ignorance", "color": "#ef56ff", "initloc": {"y": 0, "x": 0}, "size": 0.009441860020160675}, {"text": "selfish", "color": "#ff1cef", "initloc": {"y": 0, "x": 0}, "size": 0.009449326433241367}, {"text": "moral", "color": "#ff4bfb", "initloc": {"y": 0, "x": 0}, "size": 0.009519191458821297}, {"text": "rational", "color": "#ed26ff", "initloc": {"y": 0, "x": 0}, "size": 0.009531990624964237}, {"text": "naive", "color": "#ff46f9", "initloc": {"y": 0, "x": 0}, "size": 0.009499618783593178}, {"text": "belief", "color": "#ff54ff", "initloc": {"y": 0, "x": 0}, "size": 0.009464229457080364}, {"text": "reasoning", "color": "#ee47ff", "initloc": {"y": 0, "x": 0}, "size": 0.00954144261777401}, {"text": "ignorant", "color": "#ff61ff", "initloc": {"y": 0, "x": 0}, "size": 0.010008927434682846}, {"text": "justify", "color": "#ff65ef", "initloc": {"y": 0, "x": 0}, "size": 0.009622901678085327}, {"text": "beliefs", "color": "#ff30ff", "initloc": {"y": 0, "x": 0}, "size": 0.009754769504070282}, {"text": "opinion", "color": "#fe60ff", "initloc": {"y": 0, "x": 0}, "size": 0.009885061532258987}, {"text": "argue", "color": "#e954ff", "initloc": {"y": 0, "x": 0}, "size": 0.009758020751178265}, {"text": "religion", "color": "#ff32ff", "initloc": {"y": 0, "x": 0}, "size": 0.009581917896866798}, {"text": "justification", "color": "#ff4afd", "initloc": {"y": 0, "x": 0}, "size": 0.009582806378602982}, {"text": "deny", "color": "#ff38ff", "initloc": {"y": 0, "x": 0}, "size": 0.009697414934635162}, {"text": "agree", "color": "#ff3fff", "initloc": {"y": 0, "x": 0}, "size": 0.009609684348106384}, {"text": "opinions", "color": "#ed4eff", "initloc": {"y": 0, "x": 0}, "size": 0.00984607171267271}], "ctm_idx": 144189, "freesurfer_idx": 236654, "hemi": "right"}