{"accuracy": 0.030510181264090594, "rgb": "#7a7591", "cb": 0, "words": [{"text": "reason", "color": "#f025ea", "initloc": {"y": 0, "x": 0}, "size": 0.002998427953571081}, {"text": "say", "color": "#ee29e4", "initloc": {"y": 0, "x": 0}, "size": 0.003003563964739442}, {"text": "sure", "color": "#d92ec1", "initloc": {"y": 0, "x": 0}, "size": 0.003011120483279228}, {"text": "seems", "color": "#dd40ff", "initloc": {"y": 0, "x": 0}, "size": 0.0030246477108448744}, {"text": "even", "color": "#c83aad", "initloc": {"y": 0, "x": 0}, "size": 0.003034922992810607}, {"text": "how", "color": "#a045c9", "initloc": {"y": 0, "x": 0}, "size": 0.0030352137982845306}, {"text": "things", "color": "#9d32db", "initloc": {"y": 0, "x": 0}, "size": 0.0030608288943767548}, {"text": "might", "color": "#d82dd7", "initloc": {"y": 0, "x": 0}, "size": 0.0033821123652160168}, {"text": "actually", "color": "#bb45e7", "initloc": {"y": 0, "x": 0}, "size": 0.0030649250838905573}, {"text": "any", "color": "#d8438d", "initloc": {"y": 0, "x": 0}, "size": 0.0030805824790149927}, {"text": "think", "color": "#db46ee", "initloc": {"y": 0, "x": 0}, "size": 0.0030857790261507034}, {"text": "yet", "color": "#c902f0", "initloc": {"y": 0, "x": 0}, "size": 0.003133525839075446}, {"text": "what", "color": "#d02ac8", "initloc": {"y": 0, "x": 0}, "size": 0.0031464258208870888}, {"text": "something", "color": "#a33acf", "initloc": {"y": 0, "x": 0}, "size": 0.0031037931330502033}, {"text": "done", "color": "#bf20cb", "initloc": {"y": 0, "x": 0}, "size": 0.003116506151854992}, {"text": "should", "color": "#f9409e", "initloc": {"y": 0, "x": 0}, "size": 0.003141069784760475}, {"text": "anything", "color": "#cc38d6", "initloc": {"y": 0, "x": 0}, "size": 0.003128764219582081}, {"text": "better", "color": "#a261ee", "initloc": {"y": 0, "x": 0}, "size": 0.0030649479012936354}, {"text": "know", "color": "#ef1ad4", "initloc": {"y": 0, "x": 0}, "size": 0.0030620377510786057}, {"text": "do", "color": "#ba38a9", "initloc": {"y": 0, "x": 0}, "size": 0.003130103927105665}], "ctm_idx": 104536, "freesurfer_idx": 205964, "hemi": "right"}