{"accuracy": 0.2280150441508072, "rgb": "#6b0910", "cb": 3, "words": [{"text": "twenty", "color": "#5f6400", "initloc": {"y": 0, "x": 0}, "size": 0.01336762122809887}, {"text": "monday", "color": "#380000", "initloc": {"y": 0, "x": 0}, "size": 0.013461310416460037}, {"text": "ten", "color": "#538700", "initloc": {"y": 0, "x": 0}, "size": 0.013508351519703865}, {"text": "month", "color": "#a10500", "initloc": {"y": 0, "x": 0}, "size": 0.014642488211393356}, {"text": "last", "color": "#a50029", "initloc": {"y": 0, "x": 0}, "size": 0.013482154347002506}, {"text": "stayed", "color": "#af001e", "initloc": {"y": 0, "x": 0}, "size": 0.013922533020377159}, {"text": "years", "color": "#bf0e00", "initloc": {"y": 0, "x": 0}, "size": 0.013780499808490276}, {"text": "friday", "color": "#380004", "initloc": {"y": 0, "x": 0}, "size": 0.013632010668516159}, {"text": "saturday", "color": "#250400", "initloc": {"y": 0, "x": 0}, "size": 0.013618964701890945}, {"text": "weeks", "color": "#a10000", "initloc": {"y": 0, "x": 0}, "size": 0.014376791194081306}, {"text": "weekend", "color": "#3a0000", "initloc": {"y": 0, "x": 0}, "size": 0.013563720509409904}, {"text": "home", "color": "#8d0000", "initloc": {"y": 0, "x": 0}, "size": 0.014620717614889145}, {"text": "spent", "color": "#9c0000", "initloc": {"y": 0, "x": 0}, "size": 0.014025988057255745}, {"text": "trip", "color": "#53000e", "initloc": {"y": 0, "x": 0}, "size": 0.013788454234600067}, {"text": "hour", "color": "#0d0019", "initloc": {"y": 0, "x": 0}, "size": 0.014245139434933662}, {"text": "days", "color": "#62000e", "initloc": {"y": 0, "x": 0}, "size": 0.014561621472239494}, {"text": "hours", "color": "#1c0013", "initloc": {"y": 0, "x": 0}, "size": 0.014918895438313484}, {"text": "months", "color": "#b70000", "initloc": {"y": 0, "x": 0}, "size": 0.015924906358122826}, {"text": "year", "color": "#802200", "initloc": {"y": 0, "x": 0}, "size": 0.01781766302883625}, {"text": "week", "color": "#5f0000", "initloc": {"y": 0, "x": 0}, "size": 0.015115659683942795}], "ctm_idx": 115351, "freesurfer_idx": 197626, "hemi": "right"}