{"accuracy": 0.1394767335811655, "rgb": "#ada3b6", "cb": 2, "words": [{"text": "believes", "color": "#ff43ff", "initloc": {"y": 0, "x": 0}, "size": 0.011415127664804459}, {"text": "whether", "color": "#ff26c5", "initloc": {"y": 0, "x": 0}, "size": 0.011547807604074478}, {"text": "obvious", "color": "#d961ff", "initloc": {"y": 0, "x": 0}, "size": 0.011502359062433243}, {"text": "statement", "color": "#ff3ff2", "initloc": {"y": 0, "x": 0}, "size": 0.011808931827545166}, {"text": "truth", "color": "#ff22ff", "initloc": {"y": 0, "x": 0}, "size": 0.011419127695262432}, {"text": "opinion", "color": "#fe60ff", "initloc": {"y": 0, "x": 0}, "size": 0.011735410429537296}, {"text": "reasoning", "color": "#ee47ff", "initloc": {"y": 0, "x": 0}, "size": 0.011463881470263004}, {"text": "clearly", "color": "#ff5cff", "initloc": {"y": 0, "x": 0}, "size": 0.011750740930438042}, {"text": "argument", "color": "#ff49f9", "initloc": {"y": 0, "x": 0}, "size": 0.011741280555725098}, {"text": "quote", "color": "#fa3aff", "initloc": {"y": 0, "x": 0}, "size": 0.01182275079190731}, {"text": "wrong", "color": "#ff3fff", "initloc": {"y": 0, "x": 0}, "size": 0.011599211022257805}, {"text": "prove", "color": "#ff2fee", "initloc": {"y": 0, "x": 0}, "size": 0.011922521516680717}, {"text": "proof", "color": "#f95cd9", "initloc": {"y": 0, "x": 0}, "size": 0.011958110146224499}, {"text": "claim", "color": "#ff5ecb", "initloc": {"y": 0, "x": 0}, "size": 0.012180431745946407}, {"text": "correct", "color": "#d36fe1", "initloc": {"y": 0, "x": 0}, "size": 0.013154350221157074}, {"text": "question", "color": "#ff0cf0", "initloc": {"y": 0, "x": 0}, "size": 0.012271602638065815}, {"text": "sentence", "color": "#ff2dde", "initloc": {"y": 0, "x": 0}, "size": 0.011986106634140015}, {"text": "true", "color": "#fe5bff", "initloc": {"y": 0, "x": 0}, "size": 0.012533067725598812}, {"text": "believe", "color": "#ff3cff", "initloc": {"y": 0, "x": 0}, "size": 0.012079080566763878}, {"text": "false", "color": "#ff7ff4", "initloc": {"y": 0, "x": 0}, "size": 0.012629533186554909}], "ctm_idx": 73082, "freesurfer_idx": 67975, "hemi": "left"}